README.txt
setup.cfg
setup.py
collective/__init__.py
collective.googleauthentication.egg-info/PKG-INFO
collective.googleauthentication.egg-info/SOURCES.txt
collective.googleauthentication.egg-info/dependency_links.txt
collective.googleauthentication.egg-info/entry_points.txt
collective.googleauthentication.egg-info/namespace_packages.txt
collective.googleauthentication.egg-info/not-zip-safe
collective.googleauthentication.egg-info/requires.txt
collective.googleauthentication.egg-info/top_level.txt
collective/googleauthentication/LICENSE
collective/googleauthentication/__init__.py
collective/googleauthentication/configure.zcml
collective/googleauthentication/skins.zcml
collective/googleauthentication/tests.py
collective/googleauthentication/browser/__init__.py
collective/googleauthentication/browser/configure.zcml
collective/googleauthentication/browser/session_token.py
collective/googleauthentication/profiles/default/memberdata_properties.xml
collective/googleauthentication/profiles/default/metadata.xml
collective/googleauthentication/profiles/default/skins.xml
collective/googleauthentication/skins/google_authentication/logged_in.cpy
collective/googleauthentication/skins/google_authentication/logged_in.cpy.metadata
docs/HISTORY.txt
docs/INSTALL.txt
docs/LICENSE.GPL
docs/LICENSE.txt