Metadata-Version: 1.0
Name: collective.googleauthentication
Version: 1.0.0
Summary: GA takes care of the user authentication upon Google Docs service
Home-page: http://svn.plone.org/svn/collective/collective.googleauthentication/
Author: D'Elia Federica
Author-email: federica.delia@redturtle.it
License: GPL
Platform: UNKNOWN
Classifier: Framework :: Plone
Classifier: Programming Language :: Python
Classifier: Topic :: Software Development :: Libraries :: Python Modules
